{
    "nodes": [
        {
            "id": 1,
            "label": "HCV Cirrhosis",
            "color": "#ffd8b0"
        },
        {
            "id": 2,
            "label": "HIV",
            "color": "#93c5ff"
        },
        {
            "id": 3,
            "label": "COPD",
            "color": "#ffbf6a"
        },
        {
            "id": 4,
            "label": "Bipolar Disorder",
            "color": "#91d7ea"
        },
        {
            "id": 5,
            "label": "PTSD",
            "color": "#e8c3ff"
        },
        {
            "id": 6,
            "label": "Abdominal Distension",
            "color": "#ffd4a9"
        },
        {
            "id": 7,
            "label": "Confusion",
            "color": "#dce7f1"
        },
        {
            "id": 8,
            "label": "Ascites",
            "color": "#b3e0ff"
        },
        {
            "id": 9,
            "label": "Portal Hypertension",
            "color": "#c4d6ff"
        },
        {
            "id": 10,
            "label": "Nodular Liver",
            "color": "#ffd8b0"
        },
        {
            "id": 11,
            "label": "Splenomegaly",
            "color": "#ff9a9e"
        },
        {
            "id": 12,
            "label": "Cholelithiasis",
            "color": "#ffd8b0"
        },
        {
            "id": 13,
            "label": "Patent Portal Veins",
            "color": "#c4d6ff"
        },
        {
            "id": 14,
            "label": "Furosemide",
            "color": "#93c5ff"
        },
        {
            "id": 15,
            "label": "Spironolactone",
            "color": "#93c5ff"
        },
        {
            "id": 16,
            "label": "Paracentesis",
            "color": "#ffd8b0"
        },
        {
            "id": 17,
            "label": "Low Sodium Diet",
            "color": "#e8c3ff"
        },
        {
            "id": 18,
            "label": "Medication Adherence",
            "color": "#dce7f1"
        },
        {
            "id": 19,
            "label": "EGD",
            "color": "#ffd8b0"
        },
        {
            "id": 20,
            "label": "Colonoscopy",
            "color": "#ffd8b0"
        },
        {
            "id": 21,
            "label": "Non-Compliance",
            "color": "#ff9a9e"
        },
        {
            "id": 22,
            "label": "Potassium Levels",
            "color": "#dce7f1"
        },
        {
            "id": 23,
            "label": "Education",
            "color": "#e8c3ff"
        },
        {
            "id": 24,
            "label": "Monitoring",
            "color": "#dce7f1"
        }
    ],
    "edges": [
        {
            "from": 1,
            "to": 8,
            "label": "cause_of"
        },
        {
            "from": 6,
            "to": 2,
            "label": "symptom_of"
        },
        {
            "from": 7,
            "to": 2,
            "label": "symptom_of"
        },
        {
            "from": 8,
            "to": 1,
            "label": "condition_related_to"
        },
        {
            "from": 9,
            "to": 1,
            "label": "complication_of"
        },
        {
            "from": 10,
            "to": 1,
            "label": "finding_in"
        },
        {
            "from": 11,
            "to": 1,
            "label": "finding_in"
        },
        {
            "from": 12,
            "to": 1,
            "label": "finding_in"
        },
        {
            "from": 13,
            "to": 1,
            "label": "finding_in"
        },
        {
            "from": 14,
            "to": 8,
            "label": "treatment_for"
        },
        {
            "from": 15,
            "to": 8,
            "label": "treatment_for"
        },
        {
            "from": 16,
            "to": 8,
            "label": "procedure_related_to"
        },
        {
            "from": 17,
            "to": 8,
            "label": "management_strategy"
        },
        {
            "from": 18,
            "to": 8,
            "label": "management_strategy"
        },
        {
            "from": 19,
            "to": 4,
            "label": "procedure_related_to"
        },
        {
            "from": 20,
            "to": 4,
            "label": "procedure_related_to"
        },
        {
            "from": 21,
            "to": 8,
            "label": "contributing_factor"
        },
        {
            "from": 21,
            "to": 2,
            "label": "contributing_factor"
        },
        {
            "from": 22,
            "to": 15,
            "label": "monitoring_parameter"
        },
        {
            "from": 23,
            "to": 8,
            "label": "future_management_strategy"
        },
        {
            "from": 24,
            "to": 8,
            "label": "future_management_strategy"
        }
    ]
}